simple_chatbot/__init__.py
simple_chatbot/chatbot.py
simple_chatbot-0.1.dist-info/METADATA
simple_chatbot-0.1.dist-info/WHEEL
simple_chatbot-0.1.dist-info/top_level.txt
simple_chatbot-0.1.dist-info/RECORD
